bear_utils/__init__.py
bear_utils/__main__.py
bear_utils/fastapi_server.py
bear_utils/_internal/__init__.py
bear_utils/_internal/_info.py
bear_utils/_internal/_version.py
bear_utils/_internal/_version.pyi
bear_utils/_internal/cli.py
bear_utils/_internal/debug.py
bear_utils/ai/__init__.py
bear_utils/ai/_common.py
bear_utils/ai/_config.py
bear_utils/ai/_parsers.py
bear_utils/ai/_types.py
bear_utils/ai/_utility.py
bear_utils/cache/__init__.py
bear_utils/cache/_cache_factory.py
bear_utils/cache/_modified_cache.py
bear_utils/cli/__init__.py
bear_utils/cli/prompt_helpers.py
bear_utils/events/__init__.py
bear_utils/events/_base_event_bus.py
bear_utils/events/_common.py
bear_utils/events/_inputs.py
bear_utils/events/_results.py
bear_utils/events/async_event_bus.py
bear_utils/events/event_bus.py
bear_utils/events/event_models.py
bear_utils/extras/__init__.py
bear_utils/extras/clipboard.py
bear_utils/graphics/__init__.py
bear_utils/graphics/image_helpers.py
bear_utils/ignore_parser/__init__.py
bear_utils/ignore_parser/base_class.py
bear_utils/ignore_parser/base_class.pyi
bear_utils/ignore_parser/common.py
bear_utils/ignore_parser/funcs.py
bear_utils/ignore_parser/ignore_parser.py
bear_utils/loggerstuffs/__init__.py
bear_utils/loggerstuffs/client.py
bear_utils/loggerstuffs/server.py
bear_utils-0.13.12.dist-info/METADATA
bear_utils-0.13.12.dist-info/WHEEL
bear_utils-0.13.12.dist-info/entry_points.txt
bear_utils-0.13.12.dist-info/RECORD
