Metadata-Version: 2.4
Name: bear-utils
Version: 0.13.12
Summary: Various utilities for Bear programmers, including a rich logging utility, a disk cache, and a SQLite database wrapper amongst other things.
Author-email: chaz <bright.lid5647@fastmail.com>
Requires-Python: >=3.13
Requires-Dist: bear-dereth>=0.5.2
Requires-Dist: bear-epoch-time>=1.2.6
Requires-Dist: codec-cub>=0.0.8
Requires-Dist: diskcache>=5.6.3
Requires-Dist: fastapi>=0.116.0
Requires-Dist: httpx>=0.28.1
Requires-Dist: lazy-bear>=0.0.7
Requires-Dist: pathspec>=0.12.1
Requires-Dist: pillow>=11.3.0
Requires-Dist: pydantic>=2.12.3
Requires-Dist: pyfiglet>=1.0.3
Requires-Dist: rich>=14.2.0
Requires-Dist: singleton-base>=1.2.4
Requires-Dist: sqlalchemy>=2.0.40
Requires-Dist: uvicorn>=0.35.0
